MANIFEST.in
setup.py
wikia_common_kibana.py
wikia_common_kibana.egg-info/PKG-INFO
wikia_common_kibana.egg-info/SOURCES.txt
wikia_common_kibana.egg-info/dependency_links.txt
wikia_common_kibana.egg-info/requires.txt
wikia_common_kibana.egg-info/top_level.txt