Metadata-Version: 2.1
Name: wikia-common-kibana
Version: 2.2.7
Summary: Run queries against Kibana's Elasticsearch 6
Home-page: https://github.com/macbre/wikia-common-kibana
Author: Wikia Engineering
Author-email: techteam-l@wikia-inc.com
License: MIT
Keywords: logstash kibana elasticsearch logging
Platform: UNKNOWN
Provides-Extra: dev
